{
  "sv" : {
    "ll#v" : {
      "tb@caimiType" : "",
      "ll#h" : {
        "et@channel" : "",
        "tv" : ""
      },
      "rg@channelRg" : {
        "rb@id80003" : "",
        "rb@id80002" : "",
        "rb@id80001" : ""
      },
       "ll@a_fake#h" : {
        "et@shenfen" : "",
        "tv" : ""
      },
        "rg@shenfenRg" : {
        "rb@shandong" : "",
        "rb@shanghai" : "",
        "rb@hunan" : ""
      },
      "ll@b_fake#h":{"tv":"","et@mobile":""},
      "ll@_fakec#h":{"tv":"","et@psw":""},
      "b@save":""
    }
  }
}